cbm_shell/__init__.py
cbm_shell/disk_image.py
cbm_shell/disk_image_path.py
cbm_shell/image_path.py
cbm_shell/image_path_base.py
cbm_shell/images.py
cbm_shell/native_path.py
cbm_shell/subdirectory.py
cbm_shell/t64_image.py
cbm_shell/t64_image_path.py
cbm_shell/tap_image.py
cbm_shell/tap_image_path.py
cbm_shell/tap_image_path_read.py
cbm_shell/tap_image_path_write.py
cbm_shell/scripts/__init__.py
cbm_shell/scripts/cbm_shell.py
cbmshell-1.16.dist-info/LICENSE
cbmshell-1.16.dist-info/METADATA
cbmshell-1.16.dist-info/WHEEL
cbmshell-1.16.dist-info/entry_points.txt
cbmshell-1.16.dist-info/top_level.txt
cbmshell-1.16.dist-info/RECORD
