Metadata-Version: 2.1
Name: cbmshell
Version: 1.16
Summary: Interactive shell to manipulate Commodore files
Home-page: https://eden.mose.org.uk/gitweb/?p=python-cbmshell.git
Author: Simon Rowe
Author-email: srowe@mose.org.uk
License: GPLv2
Classifier: Development Status :: 5 - Production/Stable
Classifier: Intended Audience :: Developers
Classifier: License :: OSI Approved :: GNU General Public License v2 (GPLv2)
Classifier: Programming Language :: Python :: 3
Classifier: Topic :: Software Development :: Libraries :: Python Modules
License-File: LICENSE
